s3_util/__init__.py
s3_util/main.py
s3util/__init__.py
s3util/main.py
s3util/operations/__init__.py
s3util/operations/editfile.py
s3util/operations/list.py
s3util/operations/printfile.py
s3util/operations/restore.py
s3util/operations/s3copy.py
s3util/operations/s3mv.py
s3util/operations/s3rm.py
s3util/utils/__init__.py
s3util/utils/pathcompleter.py
s3util/utils/pathparser.py
s3util/utils/test.py
s3util-0.0.1.dist-info/LICENSE
s3util-0.0.1.dist-info/METADATA
s3util-0.0.1.dist-info/WHEEL
s3util-0.0.1.dist-info/entry_points.txt
s3util-0.0.1.dist-info/top_level.txt
s3util-0.0.1.dist-info/RECORD
